src/__init__.py
src/s3_lifecycle/__init__.py
src/s3_lifecycle/diff.py
src/s3_lifecycle/exceptions.py
src/s3_lifecycle/manager.py
src/s3_lifecycle/policy.py
src/s3_lifecycle/validators.py
tests/__init__.py
tests/test_diff.py
tests/test_manager_mocked.py
tests/test_policy_validation.py
s3_lifecycle-0.1.2.dist-info/METADATA
s3_lifecycle-0.1.2.dist-info/WHEEL
s3_lifecycle-0.1.2.dist-info/top_level.txt
s3_lifecycle-0.1.2.dist-info/RECORD
