Metadata-Version: 2.4
Name: s3-lifecycle
Version: 0.1.2
Summary: A Python library to manage S3 lifecycle policies
Home-page: https://github.com/FernandoOLI/s3_lifecycle
Author: Fernando Oliveira Pereira
Author-email: Fernando Oliveira Pereira <oliveira-fernando1@hotmail.com>
License: MIT
Project-URL: Homepage, https://github.com/FernandoOLI/s3_lifecycle
Project-URL: Issues, https://github.com/FernandoOLI/s3_lifecycle/issues
Keywords: aws,s3,s3_lifecycle
Classifier: Programming Language :: Python :: 3
Classifier: License :: OSI Approved :: MIT License
Classifier: Operating System :: OS Independent
Requires-Python: >=3.6
Requires-Dist: pytest
Requires-Dist: moto
Requires-Dist: pydantic
Requires-Dist: boto3
Requires-Dist: botocore
Dynamic: author
Dynamic: home-page
Dynamic: requires-python
